examples/__init__.py
examples/reglo_cpf/__init__.py
examples/reglo_cpf/basic.py
examples/reglo_icc/__init__.py
examples/reglo_icc/basic.py
examples/reglo_icc/basic_4_channel.py
ismatec/__init__.py
ismatec/__version__.py
ismatec/errors.py
ismatec/peristaltic_pump.py
ismatec/piston_pump.py
ismatec/utilities.py
ismatec-1.5.2.dist-info/LICENSE
ismatec-1.5.2.dist-info/METADATA
ismatec-1.5.2.dist-info/WHEEL
ismatec-1.5.2.dist-info/top_level.txt
ismatec-1.5.2.dist-info/RECORD
