Metadata-Version: 2.1
Name: ismatec
Version: 1.5.2
Summary: Unofficial package to control ISMATEC products. We are not affiliated with ISMATEC.
Home-page: https://gitlab.com/heingroup/ismatec
Author: Veronica Lai // Hein Group
License: UNKNOWN
Platform: UNKNOWN
Classifier: Programming Language :: Python :: 3
Requires-Python: >=3.6
Requires-Dist: ftdi-serial
